pyrusquant/__init__.py
pyrusquant/async_parsing.py
pyrusquant/symbols_gigapack.py
pyrusquant/symbols_gigapack_async.py
pyrusquant-0.1.dist-info/LICENSE.txt
pyrusquant-0.1.dist-info/METADATA
pyrusquant-0.1.dist-info/WHEEL
pyrusquant-0.1.dist-info/top_level.txt
pyrusquant-0.1.dist-info/RECORD
