Metadata-Version: 2.1
Name: pyrusquant
Version: 0.1
Summary: Pyrusquant is a package for interaction with alternative data, trading API of different exchanges and brokers'
Home-page: https://github.com/arbuzovv/pyrusquant
Author: Arbuzov Vyacheslav, Petukhov Maksim
Author-email: Vyacheslav Arbuzov <noreply@github.com>
License: # pyrusquant
Classifier: License :: OSI Approved :: Apache Software License
Classifier: Operating System :: OS Independent
Classifier: Programming Language :: Python :: 3
Requires-Python: >=3.7
License-File: LICENSE.txt
Requires-Dist: aiohttp ==3.9.1
Requires-Dist: aiosignal ==1.3.1
Requires-Dist: attrs ==23.1.0
Requires-Dist: certifi ==2023.11.17
Requires-Dist: charset-normalizer ==3.3.2
Requires-Dist: frozenlist ==1.4.0
Requires-Dist: idna ==3.6
Requires-Dist: multidict ==6.0.4
Requires-Dist: numpy ==1.26.2
Requires-Dist: pandas ==2.1.3
Requires-Dist: python-dateutil ==2.8.2
Requires-Dist: pytz ==2023.3.post1
Requires-Dist: requests ==2.31.0
Requires-Dist: six ==1.16.0
Requires-Dist: tzdata ==2023.3
Requires-Dist: urllib3 ==2.1.0
Requires-Dist: yarl ==1.9.4
